imuthes/.git
imuthes/.gitignore
imuthes/README.md
imuthes/__init__.py
imuthes/classproperty.py
imuthes/cli.py
imuthes/configuration.py
imuthes/display_table.py
imuthes/make_link.py
imuthes/mapping.py
imuthes/singleton.py
imuthes-0.1.0.dist-info/METADATA
imuthes-0.1.0.dist-info/WHEEL
imuthes-0.1.0.dist-info/RECORD
